agents/__init__.py
agents/agents.py
environments/__init__.py
environments/environment.py
models/__init__.py
models/llm_model.py
tools/__init__.py
tools/image_analysis_tool.py
tools/rag_tool.py
tools/tools.py
tools/webscraper_tool.py
tools/wikipedia_tool.py
tools/youtube_tool.py
ensembleai-1.2.7.dist-info/METADATA
ensembleai-1.2.7.dist-info/WHEEL
ensembleai-1.2.7.dist-info/top_level.txt
ensembleai-1.2.7.dist-info/RECORD
