Metadata-Version: 2.2
Name: ensembleai
Version: 1.2.7
Summary: A Python package for AI-MultiModal MultiAgents methods and tools.
Home-page: https://github.com/yourusername/ensembleai
Author: Shreyas Jain, Prakhar Jain, Kushagra Jain
Author-email: shreyasjain.feb@gmail.com, prakharjain2004@gmail.com, kushagrajain.feb@gmail.com
License: MIT
Classifier: Development Status :: 3 - Alpha
Classifier: Intended Audience :: Developers
Classifier: License :: OSI Approved :: MIT License
Classifier: Programming Language :: Python :: 3
Classifier: Programming Language :: Python :: 3.6
Classifier: Programming Language :: Python :: 3.7
Classifier: Programming Language :: Python :: 3.8
Classifier: Programming Language :: Python :: 3.9
Requires-Python: >=3.6
Requires-Dist: groq
Requires-Dist: wikipedia-api
Requires-Dist: youtube_transcript_api
Requires-Dist: PyPDF2
Requires-Dist: faiss-cpu
Requires-Dist: langchain_community
Requires-Dist: requests
Requires-Dist: beautifulsoup4
Requires-Dist: pandas
Requires-Dist: google-api-python-client
Requires-Dist: sentence-transformers
Dynamic: author
Dynamic: author-email
Dynamic: classifier
Dynamic: description
Dynamic: description-content-type
Dynamic: home-page
Dynamic: license
Dynamic: requires-dist
Dynamic: requires-python
Dynamic: summary
